kouyierr/__init__.py
kouyierr/index.py
kouyierr/main.py
kouyierr/commands/__init__.py
kouyierr/commands/documentation/__init__.py
kouyierr/commands/documentation/generate.py
kouyierr/commands/ghproject/__init__.py
kouyierr/commands/ghproject/generate.py
kouyierr/commands/invoice/__init__.py
kouyierr/commands/invoice/generate.py
kouyierr/utils/__init__.py
kouyierr/utils/helper.py
kouyierr-0.0.12.dist-info/LICENSE
kouyierr-0.0.12.dist-info/METADATA
kouyierr-0.0.12.dist-info/WHEEL
kouyierr-0.0.12.dist-info/entry_points.txt
kouyierr-0.0.12.dist-info/top_level.txt
kouyierr-0.0.12.dist-info/zip-safe
kouyierr-0.0.12.dist-info/RECORD
