Metadata-Version: 2.1
Name: kouyierr
Version: 0.0.12
Summary: Document Generator, aka Doc As Code
Home-page: https://github.com/vmdude/kouyierr
Author: vmdude
Author-email: frederic@martin.lc
License: MIT
Keywords: aws
Platform: UNKNOWN
Classifier: Programming Language :: Python :: 3.8
Requires-Dist: boto3
Requires-Dist: click
Requires-Dist: ghapi (==0.1.16)
Requires-Dist: Jinja2
Requires-Dist: pdfkit
Requires-Dist: pypandoc
Requires-Dist: rich
Requires-Dist: texlivemetadata
Requires-Dist: yamllint
Provides-Extra: test
Requires-Dist: mock (==3.0.5) ; extra == 'test'
Requires-Dist: pytest (==5.0.1) ; extra == 'test'
Requires-Dist: pytest-runner (==5.1) ; extra == 'test'
Requires-Dist: pytest-pylint (==0.14) ; extra == 'test'
Requires-Dist: pytest-cov (==2.7.1) ; extra == 'test'
Requires-Dist: pylint (==2.3.1) ; extra == 'test'
Requires-Dist: zest.releaser ; extra == 'test'
